avit_entropy/__init__.py
avit_entropy/estimator.py
avit_entropy/utils.py
avit_entropy-1.0.0.dist-info/LICENSE
avit_entropy-1.0.0.dist-info/METADATA
avit_entropy-1.0.0.dist-info/WHEEL
avit_entropy-1.0.0.dist-info/top_level.txt
avit_entropy-1.0.0.dist-info/RECORD
