Metadata-Version: 2.2
Name: avit-entropy
Version: 1.0.0
Summary: A python module for calculating entropy of autonous vehicle scenarios using information theory.
Home-page: https://github.com/AkbasLab/avit-entropy
Author: Quentin Goss, Dr. Mustafa Ilhan Akbas
Author-email: gossq@my.erau.edu, akbasm@erau.edu
Project-URL: Bug Tracker, https://github.com/AkbasLab/avit-entropy/issues
Classifier: Programming Language :: Python :: 3
Classifier: License :: OSI Approved :: MIT License
Classifier: Operating System :: OS Independent
Requires-Python: >= 3.9
License-File: LICENSE
Requires-Dist: sim-bug-tools
Requires-Dist: shapely>=1.0.0
Dynamic: author
Dynamic: author-email
Dynamic: classifier
Dynamic: description
Dynamic: description-content-type
Dynamic: home-page
Dynamic: project-url
Dynamic: requires-dist
Dynamic: requires-python
Dynamic: summary
